telaio/__init__.py
telaio/video_file.py
telaio-0.0.3.dist-info/LICENSE
telaio-0.0.3.dist-info/METADATA
telaio-0.0.3.dist-info/WHEEL
telaio-0.0.3.dist-info/top_level.txt
telaio-0.0.3.dist-info/RECORD
