Metadata-Version: 2.1
Name: telaio
Version: 0.0.3
Summary: A toolset to work with video files
Author-email: Dzmitry Plashchynski <plashchynski@gmail.com>
Project-URL: Homepage, https://github.com/plashchynski/telaio
Project-URL: Bug Tracker, https://github.com/plashchynski/telaio/issues
Classifier: Programming Language :: Python :: 3
Classifier: License :: OSI Approved :: MIT License
Classifier: Operating System :: OS Independent
Requires-Python: >=3.7
License-File: LICENSE
Requires-Dist: av (>=10.0.0)
Requires-Dist: numpy (>=1.18.5)
Requires-Dist: ffmpeg-python (>=0.2.0)
Requires-Dist: opencv-python (>=4.7.0.68)
